README.rst
setup.py
django_metasettings.egg-info/PKG-INFO
django_metasettings.egg-info/SOURCES.txt
django_metasettings.egg-info/dependency_links.txt
django_metasettings.egg-info/not-zip-safe
django_metasettings.egg-info/top_level.txt
metasettings/__init__.py
metasettings/choices.py
metasettings/compat.py
metasettings/context_processors.py
metasettings/exceptions.py
metasettings/fields.py
metasettings/helpers.py
metasettings/models.py
metasettings/openexchangerates.py
metasettings/settings.py
metasettings/signals.py
metasettings/timezone.py
metasettings/urls.py
metasettings/util.py
metasettings/views.py
metasettings/management/__init__.py
metasettings/management/commands/__init__.py
metasettings/management/commands/sync_rates.py
metasettings/south_migrations/0001_initial.py
metasettings/south_migrations/0002_auto__add_field_currencyrate_month__add_field_currencyrate_year.py
metasettings/south_migrations/0003_auto__chg_field_currencyrate_rate.py
metasettings/south_migrations/__init__.py
metasettings/templatetags/__init__.py
metasettings/templatetags/metasettings_tags.py
metasettings/tests/__init__.py
metasettings/tests/models.py
metasettings/tests/settings.py
metasettings/tests/test_commands.py
metasettings/tests/test_fields.py
metasettings/tests/test_models.py
metasettings/tests/urls.py