Metadata-Version: 1.1
Name: django-metasettings
Version: 0.3.4
Summary: A reusable Django application to control the currency rate and favorite language code, inspired by etsy
Home-page: http://github.com/thoas/django-metasettings
Author: Florent Messa
Author-email: florent.messa@gmail.com
License: UNKNOWN
Platform: UNKNOWN
Classifier: Environment :: Web Environment
Classifier: Intended Audience :: Developers
Classifier: License :: OSI Approved :: MIT License
Classifier: Operating System :: OS Independent
Classifier: Programming Language :: Python
Classifier: Topic :: Utilities
